AUTHORS
CHANGELOG.rst
LICENSE
MANIFEST.in
README.rst
setup.py
django_slowtests/__init__.py
django_slowtests/models.py
django_slowtests/testrunner.py
django_slowtests.egg-info/PKG-INFO
django_slowtests.egg-info/SOURCES.txt
django_slowtests.egg-info/dependency_links.txt
django_slowtests.egg-info/not-zip-safe
django_slowtests.egg-info/requires.txt
django_slowtests.egg-info/top_level.txt
django_slowtests/tests/__init__.py
django_slowtests/tests/fake.py
django_slowtests/tests/models.py
django_slowtests/tests/tests.py
django_slowtests/tests/urls.py